README.md
setup.cfg
setup.py
convolut_telegram/__init__.py
convolut_telegram/settings.py
convolut_telegram.egg-info/PKG-INFO
convolut_telegram.egg-info/SOURCES.txt
convolut_telegram.egg-info/dependency_links.txt
convolut_telegram.egg-info/not-zip-safe
convolut_telegram.egg-info/requires.txt
convolut_telegram.egg-info/top_level.txt
convolut_telegram/constants/__init__.py
convolut_telegram/constants/telegram_mode.py
convolut_telegram/logger/__init__.py
convolut_telegram/logger/telegram.py