Metadata-Version: 2.1
Name: convolut-telegram
Version: 0.0.2
Summary: Telegram integrations for convolut framework
Home-page: https://github.com/convolut/convolut-telegram
Author: Andrey Avdeev
Author-email: seorazer@gmail.com
License: Apache 2.0
Keywords: convolut telegram
Platform: UNKNOWN
Requires-Python: >=3.7
